jmth/__init__.py
jmth/jmth.py
jmth-0.1.1.dist-info/licenses/LICENSE
jmth-0.1.1.dist-info/METADATA
jmth-0.1.1.dist-info/WHEEL
jmth-0.1.1.dist-info/top_level.txt
jmth-0.1.1.dist-info/RECORD
