Metadata-Version: 2.4
Name: jmth
Version: 0.1.1
Summary: Simple math library: volume cube & solve SPLDV
Author-email: Galih Julian <membventra@gmail.com>
License: MIT
Requires-Python: >=3.7
License-File: LICENSE
Dynamic: license-file
